jsz/globalhunter/__init__.py
jsz/globalhunter/main.py
jsz.globalhunter-0.0.2.dist-info/LICENSE.txt
jsz.globalhunter-0.0.2.dist-info/METADATA
jsz.globalhunter-0.0.2.dist-info/WHEEL
jsz.globalhunter-0.0.2.dist-info/top_level.txt
jsz.globalhunter-0.0.2.dist-info/RECORD
